fastapi_shell/__about__.py
fastapi_shell/__init__.py
fastapi_shell/__main__.py
fastapi_shell-0.1.2.dist-info/METADATA
fastapi_shell-0.1.2.dist-info/WHEEL
fastapi_shell-0.1.2.dist-info/licenses/LICENSE.txt
fastapi_shell-0.1.2.dist-info/RECORD
