Metadata-Version: 2.1
Name: fastapi-shell
Version: 0.1.2
Summary: An ipython shell for fastapi which automatically imports code and optionally opens a database connection
Project-URL: Documentation, https://github.com/unknown/fastapi-shell#readme
Project-URL: Issues, https://github.com/unknown/fastapi-shell/issues
Project-URL: Source, https://github.com/unknown/fastapi-shell
Author-email: jpribyl <jpribyl@github.io>
License-Expression: MIT
License-File: LICENSE.txt
Classifier: Development Status :: 4 - Beta
Classifier: Programming Language :: Python
Classifier: Programming Language :: Python :: 3.8
Classifier: Programming Language :: Python :: 3.9
Classifier: Programming Language :: Python :: 3.10
Classifier: Programming Language :: Python :: 3.11
Classifier: Programming Language :: Python :: Implementation :: CPython
Classifier: Programming Language :: Python :: Implementation :: PyPy
Requires-Python: >=3.9
Requires-Dist: ipython==8.6.0
Requires-Dist: prompt-toolkit==3.0.30
